{
  "project_info": {
    "project_number": "452750399942",
    "firebase_url": "https://fir-funai.firebaseio.com",
    "project_id": "fir-funai",
    "storage_bucket": "fir-funai.appspot.com"
  },
  "client": [
    {
      "client_info": {
        "mobilesdk_app_id": "1:452750399942:android:931f3736303197f4947ac7",
        "android_client_info": {
          "package_name": "com.raym.kalk"
        }
      },
      "oauth_client": [
        {
          "client_id": "452750399942-oml0en1v9jkku2qmnrptufi1ujquqpbk.apps.googleusercontent.com",
          "client_type": 3
        }
      ],
      "api_key": [
        {
          "current_key": "AIzaSyB2CGRtxg-MEoXcGGWcbPxpRmOGMYr1Ids"
        }
      ],
      "services": {
        "appinvite_service": {
          "other_platform_oauth_client": [
            {
              "client_id": "452750399942-oml0en1v9jkku2qmnrptufi1ujquqpbk.apps.googleusercontent.com",
              "client_type": 3
            }
          ]
        }
      }
    },
    {
      "client_info": {
        "mobilesdk_app_id": "1:452750399942:android:f7c4522ec9070dc9947ac7",
        "android_client_info": {
          "package_name": "com.raym.spidmart_delivery"
        }
      },
      "oauth_client": [
        {
          "client_id": "452750399942-oml0en1v9jkku2qmnrptufi1ujquqpbk.apps.googleusercontent.com",
          "client_type": 3
        }
      ],
      "api_key": [
        {
          "current_key": "AIzaSyB2CGRtxg-MEoXcGGWcbPxpRmOGMYr1Ids"
        }
      ],
      "services": {
        "appinvite_service": {
          "other_platform_oauth_client": [
            {
              "client_id": "452750399942-oml0en1v9jkku2qmnrptufi1ujquqpbk.apps.googleusercontent.com",
              "client_type": 3
            }
          ]
        }
      }
    },
    {
      "client_info": {
        "mobilesdk_app_id": "1:452750399942:android:f1f5f42e487693ca947ac7",
        "android_client_info": {
          "package_name": "com.raym.spidmart_store"
        }
      },
      "oauth_client": [
        {
          "client_id": "452750399942-oml0en1v9jkku2qmnrptufi1ujquqpbk.apps.googleusercontent.com",
          "client_type": 3
        }
      ],
      "api_key": [
        {
          "current_key": "AIzaSyB2CGRtxg-MEoXcGGWcbPxpRmOGMYr1Ids"
        }
      ],
      "services": {
        "appinvite_service": {
          "other_platform_oauth_client": [
            {
              "client_id": "452750399942-oml0en1v9jkku2qmnrptufi1ujquqpbk.apps.googleusercontent.com",
              "client_type": 3
            }
          ]
        }
      }
    },
    {
      "client_info": {
        "mobilesdk_app_id": "1:452750399942:android:bc67633474bd9a84947ac7",
        "android_client_info": {
          "package_name": "com.raym.spidmart_user"
        }
      },
      "oauth_client": [
        {
          "client_id": "452750399942-oml0en1v9jkku2qmnrptufi1ujquqpbk.apps.googleusercontent.com",
          "client_type": 3
        }
      ],
      "api_key": [
        {
          "current_key": "AIzaSyB2CGRtxg-MEoXcGGWcbPxpRmOGMYr1Ids"
        }
      ],
      "services": {
        "appinvite_service": {
          "other_platform_oauth_client": [
            {
              "client_id": "452750399942-oml0en1v9jkku2qmnrptufi1ujquqpbk.apps.googleusercontent.com",
              "client_type": 3
            }
          ]
        }
      }
    }
  ],
  "configuration_version": "1"
}